debulog/__init__.py
debulog-1.5.0.dist-info/licenses/LICENSE
debulog-1.5.0.dist-info/METADATA
debulog-1.5.0.dist-info/WHEEL
debulog-1.5.0.dist-info/top_level.txt
debulog-1.5.0.dist-info/RECORD
