Metadata-Version: 2.4
Name: debulog
Version: 1.5.0
Summary: A package for debuging and logging to output console. Someday maybe to webhook.
Author-email: IgooGG <igo@igocheap.run.place>
License:                     GNU AFFERO GENERAL PUBLIC LICENSE
Classifier: Programming Language :: Python :: 3
Classifier: License :: OSI Approved :: MIT License
Classifier: Operating System :: OS Independent
Requires-Python: >=3.6
License-File: LICENSE
Dynamic: license-file
